gym_grand_prix/__init__.py
gym_grand_prix/wrappers.py
gym_grand_prix/envs/__init__.py
gym_grand_prix/envs/grand_prix_env.py
gym_grand_prix/envs/run_car.py
gym_grand_prix/envs/cars/__init__.py
gym_grand_prix/envs/cars/agent.py
gym_grand_prix/envs/cars/physics.py
gym_grand_prix/envs/cars/track.py
gym_grand_prix/envs/cars/utils.py
gym_grand_prix/envs/cars/world.py
gym_grand_prix/envs/learning_algorithms/__init__.py
gym_grand_prix/envs/learning_algorithms/network.py
gym_grand_prix-0.2.3.dist-info/LICENSE
gym_grand_prix-0.2.3.dist-info/METADATA
gym_grand_prix-0.2.3.dist-info/WHEEL
gym_grand_prix-0.2.3.dist-info/top_level.txt
gym_grand_prix-0.2.3.dist-info/RECORD
