Metadata-Version: 2.1
Name: gym-grand-prix
Version: 0.2.3
Summary: Gym GrandPrix Env
Home-page: https://github.com/boangri/gym-grand-prix
Author: Boris Gribovskiy
Author-email: xinu@yandex.ru
License: MIT License
Platform: UNKNOWN
Requires-Python: >=3.6
Requires-Dist: gym
Requires-Dist: numpy
Requires-Dist: pygame
